<?xml version="1.0" encoding="UTF-8" standalone="no"?>


<datamodel-type xmlns="http://www.efaps.org/xsd"
    xmlns:xsi="http://www.w3.org/2001/XMLSchema-instance"
    xsi:schemaLocation="http://www.efaps.org/xsd http://www.efaps.org/xsd/eFaps_1.0.xsd">
    <uuid>1085c527-9242-48ac-af1b-9371f6cf977c</uuid>
    <file-application>eFapsApp-Construction</file-application>
    <definition>
        <version-expression>(version==latest)</version-expression>
        <name>Construction_CostEstimatePositionSale</name>
        <parent>Construction_CostEstimatePositionAbstract</parent>
        <attribute>
            <name>CostEstimateLink</name>
            <type>Link</type>
            <typelink>Construction_CostEstimateSale</typelink>
            <sqltable>Sales_PositionAbstractSQLTable</sqltable>
            <sqlcolumn>DOCID</sqlcolumn>
        </attribute>
    </definition>
</datamodel-type>